Metadata-Version: 2.1
Name: pypi-name-cli
Version: 1.0.3
Summary: Check whether a package name is available on PyPI
Home-page: https://yoginth.com
Author: Yoginth
Author-email: me@yoginth.com
Maintainer: Yoginth
Maintainer-email: me@yoginth.com
License: MIT
Project-URL: Source, https://gitlab.com/yoginth/pypi_name_cli
Keywords: PyPI,CLI,Name Checker,Package Name
Platform: UNKNOWN
Classifier: Programming Language :: Python
Classifier: Natural Language :: English
Classifier: Environment :: Console
Classifier: Operating System :: OS Independent
Classifier: Intended Audience :: End Users/Desktop
Classifier: License :: OSI Approved :: MIT License
